nonocaptcha/__init__.py
nonocaptcha/audio.py
nonocaptcha/base.py
nonocaptcha/exceptions.py
nonocaptcha/image.py
nonocaptcha/launcher.py
nonocaptcha/nonocaptcha.example.yaml
nonocaptcha/proxy.py
nonocaptcha/solver.py
nonocaptcha/speech.py
nonocaptcha/util.py
nonocaptcha/data/deface.html
nonocaptcha/data/jquery.js
nonocaptcha/data/override.js
testing/__init__.py
testing/run.py
testing/speech.py
testing/util.py
nonocaptcha-2.0.1.dist-info/LICENSE.rst
nonocaptcha-2.0.1.dist-info/METADATA
nonocaptcha-2.0.1.dist-info/WHEEL
nonocaptcha-2.0.1.dist-info/top_level.txt
nonocaptcha-2.0.1.dist-info/RECORD
